django2puml/__init__.py
django2puml/asgi.py
django2puml/settings.py
django2puml/urls.py
django2puml/wsgi.py
puml_generator/__init__.py
puml_generator/apps.py
puml_generator/management/__init__.py
puml_generator/management/commands/__init__.py
puml_generator/management/commands/generate_puml.py
puml_generator/management/commands/utils/__init__.py
puml_generator/management/commands/utils/utils.py
django_model2puml-0.3.0.dist-info/LICENSE
django_model2puml-0.3.0.dist-info/METADATA
django_model2puml-0.3.0.dist-info/WHEEL
django_model2puml-0.3.0.dist-info/top_level.txt
django_model2puml-0.3.0.dist-info/RECORD
