Metadata-Version: 2.1
Name: django-model2puml
Version: 0.3.0
Summary: A Django app to generate PlantUML diagram of project models.
Home-page: https://github.com/sen-den/django-model2puml
Author: Denis Senchishen
Author-email: dsenchishen@icloud.com
License: MIT
Classifier: Environment :: Web Environment
Classifier: Framework :: Django
Classifier: Intended Audience :: Developers
Classifier: License :: OSI Approved :: MIT License
Classifier: Operating System :: OS Independent
Classifier: Programming Language :: Python
Classifier: Programming Language :: Python :: 3
Classifier: Topic :: Internet :: WWW/HTTP
Classifier: Topic :: Internet :: WWW/HTTP :: Dynamic Content
License-File: LICENSE
